dontforget.py
dontforget-0.0.2.dist-info/LICENSE
dontforget-0.0.2.dist-info/WHEEL
dontforget-0.0.2.dist-info/METADATA
dontforget-0.0.2.dist-info/RECORD
