Metadata-Version: 2.1
Name: dontforget
Version: 0.0.2
Summary: Cache the results of expensive functions
Home-page: https://github.com/jelford/dontforget
License: UNKNOWN
Keywords: caching
Author: James Elford
Author-email: james.p.elford@gmail.com
Requires-Python: >=3.6
Classifier: License :: OSI Approved :: Apache Software License
Classifier: Intended Audience :: Developers
Classifier: Programming Language :: Python :: 3
Classifier: Topic :: Software Development :: Libraries :: Python Modules
